protobuf_protoc_bin/__init__.py
protobuf_protoc_bin/_version.py
protobuf_protoc_bin-33.5.data/data/include/google/protobuf/any.proto
protobuf_protoc_bin-33.5.data/data/include/google/protobuf/api.proto
protobuf_protoc_bin-33.5.data/data/include/google/protobuf/cpp_features.proto
protobuf_protoc_bin-33.5.data/data/include/google/protobuf/descriptor.proto
protobuf_protoc_bin-33.5.data/data/include/google/protobuf/duration.proto
protobuf_protoc_bin-33.5.data/data/include/google/protobuf/empty.proto
protobuf_protoc_bin-33.5.data/data/include/google/protobuf/field_mask.proto
protobuf_protoc_bin-33.5.data/data/include/google/protobuf/go_features.proto
protobuf_protoc_bin-33.5.data/data/include/google/protobuf/java_features.proto
protobuf_protoc_bin-33.5.data/data/include/google/protobuf/source_context.proto
protobuf_protoc_bin-33.5.data/data/include/google/protobuf/struct.proto
protobuf_protoc_bin-33.5.data/data/include/google/protobuf/timestamp.proto
protobuf_protoc_bin-33.5.data/data/include/google/protobuf/type.proto
protobuf_protoc_bin-33.5.data/data/include/google/protobuf/wrappers.proto
protobuf_protoc_bin-33.5.data/data/include/google/protobuf/compiler/plugin.proto
protobuf_protoc_bin-33.5.data/scripts/protoc.exe
protobuf_protoc_bin-33.5.dist-info/METADATA
protobuf_protoc_bin-33.5.dist-info/WHEEL
protobuf_protoc_bin-33.5.dist-info/top_level.txt
protobuf_protoc_bin-33.5.dist-info/RECORD
