Metadata-Version: 2.4
Name: protobuf-protoc-bin
Version: 33.5
Summary: Pip package to host the protobuf protoc binary
Author-email: Robert Roos <robert.roos@demcon.com>
Project-URL: Repository, https://github.com/RobertoRoos/protobuf-protoc-bin
Project-URL: Issues, https://github.com/RobertoRoos/protobuf-protoc-bin/issues
Project-URL: Protobuf, https://protobuf.dev/
Project-URL: Protobuf Github, https://github.com/protocolbuffers/protobuf
Requires-Python: >=2.7
